stsdk/__init__.py
stsdk/api/http/__init__.py
stsdk/api/http/dms.py
stsdk/api/http/oms.py
stsdk/api/http/sms.py
stsdk/api/ws/__init__.py
stsdk/api/ws/dms.py
stsdk/api/ws/oms.py
stsdk/common/__init__.py
stsdk/common/cache_key.py
stsdk/common/constant.py
stsdk/common/env.py
stsdk/common/exception.py
stsdk/common/key.py
stsdk/common/signal_key.py
stsdk/config/__init__.py
stsdk/config/config.json
stsdk/config/pre.config.json
stsdk/config/prod.config.json
stsdk/config/stage.config.json
stsdk/config/test.config.json
stsdk/model/__init__.py
stsdk/model/instrument.py
stsdk/model/order_manager.py
stsdk/model/position_manager.py
stsdk/model/strategy_base.py
stsdk/model/strategy_module.py
stsdk/test/Stresstest/Stress_klines.py
stsdk/test/Stresstest/mongoBDtest.py
stsdk/test/Stresstest/stressone.py
stsdk/test/__init__.py
stsdk/test/aliyun_log_test.py
stsdk/test/bbo_ws.py
stsdk/test/bbo_ws_main.py
stsdk/test/blinker_block_test.py
stsdk/test/blinker_test.py
stsdk/test/cache_test.py
stsdk/test/case/__init__.py
stsdk/test/case/order.py
stsdk/test/constants.py
stsdk/test/create_account.py
stsdk/test/main.py
stsdk/test/metric_test.py
stsdk/test/ordertest/CreatePosition.py
stsdk/test/ordertest/GetOrderFormPositionId.py
stsdk/test/ordertest/__init__.py
stsdk/test/ordertest/assets/style.css
stsdk/test/ordertest/conftest.py
stsdk/test/ordertest/initialization.py
stsdk/test/ordertest/placeOrder.py
stsdk/test/ordertest/pmsinit.py
stsdk/test/ordertest/position_test.py
stsdk/test/ordertest/pytest.ini
stsdk/test/ordertest/reports/assets/style.css
stsdk/test/ordertest/stagegymoduletest.py
stsdk/test/ordertest/test_Kline.py
stsdk/test/ordertest/test_cancel_all_outstanding_orders.py
stsdk/test/ordertest/test_change_leverage.py
stsdk/test/ordertest/test_close_all_positions.py
stsdk/test/ordertest/test_get_all_outstanding_orders.py
stsdk/test/ordertest/test_order_closed_loop.py
stsdk/test/ordertest/test_order_empty_multiple.py
stsdk/test/ordertest/test_position_model.py
stsdk-0.3.3.dist-info/METADATA
stsdk-0.3.3.dist-info/WHEEL
stsdk-0.3.3.dist-info/entry_points.txt
stsdk-0.3.3.dist-info/RECORD
