Metadata-Version: 2.1
Name: stsdk
Version: 0.3.3
Summary: this is for at trade strategy module
Author: stark
Author-email: yangwang@web3.com
Requires-Python: >=3.10,<4.0
Classifier: Programming Language :: Python :: 3
Classifier: Programming Language :: Python :: 3.10
Classifier: Programming Language :: Python :: 3.11
Classifier: Programming Language :: Python :: 3.12
Requires-Dist: aiohttp (>=3.8.6,<4.0.0)
Requires-Dist: asyncio (>=3.4.3,<4.0.0)
Requires-Dist: blinker (>=1.7.0,<2.0.0)
Requires-Dist: cacheout (>=0.15.0,<0.16.0)
Requires-Dist: chardet (>=5.2.0,<6.0.0)
Requires-Dist: httpx (>=0.25.0,<0.26.0)
Requires-Dist: janus (>=1.0.0,<2.0.0)
Requires-Dist: locust (>=2.20.1,<3.0.0)
Requires-Dist: loguru (>=0.7.2,<0.8.0)
Requires-Dist: numpy (==1.24.3)
Requires-Dist: openpyxl (>=3.1.2,<4.0.0)
Requires-Dist: pandas (==2.0.3)
Requires-Dist: prometheus-client (>=0.19.0,<0.20.0)
Requires-Dist: pyarrow (>=15.0.0,<16.0.0)
Requires-Dist: redis (>=5.0.3,<6.0.0)
Requires-Dist: rel (>=0.4.9,<0.5.0)
Requires-Dist: requests (>=2.31.0,<3.0.0)
Requires-Dist: sortedcontainers (>=2.4.0,<3.0.0)
Requires-Dist: ujson (>=5.8.0,<6.0.0)
Requires-Dist: websockets (>=11.0.3,<12.0.0)
